GazeboMotionCapture/__init__.py
GazeboMotionCapture-0.1.3.dist-info/DESCRIPTION.rst
GazeboMotionCapture-0.1.3.dist-info/METADATA
GazeboMotionCapture-0.1.3.dist-info/RECORD
GazeboMotionCapture-0.1.3.dist-info/WHEEL
GazeboMotionCapture-0.1.3.dist-info/metadata.json
GazeboMotionCapture-0.1.3.dist-info/top_level.txt
