Metadata-Version: 2.0
Name: GazeboMotionCapture
Version: 0.1.3
Summary: Motion Capture System Simulator Base on Gazebo, can be use for vehicle position Estimate
Home-page: https://github.com/PixelBatStudios/GazeboMotionCapture
Author: Huibean Luo
Author-email: huibean@users.noreply.github.com
License: MIT
Keywords: motion capture,vicon,optitrack,indoor positioning,px4,ardupilot
Platform: UNKNOWN
Classifier: Development Status :: 4 - Beta
Classifier: Intended Audience :: Developers
Classifier: Topic :: Software Development :: Embedded Systems
Classifier: Topic :: Software Development :: Libraries :: Python Modules
Classifier: Topic :: Scientific/Engineering :: Mathematics
Classifier: Topic :: Scientific/Engineering :: Physics
Classifier: Topic :: Scientific/Engineering :: Visualization
Classifier: License :: OSI Approved :: MIT License
Classifier: Programming Language :: Python :: 2.7
Classifier: Programming Language :: Python :: 3
Classifier: Programming Language :: Python :: 3.1
Classifier: Programming Language :: Python :: 3.2
Classifier: Programming Language :: Python :: 3.3
Classifier: Programming Language :: Python :: 3.4
Classifier: Programming Language :: Python :: 3.5
Requires-Dist: numpy
Requires-Dist: pygazebo
Requires-Dist: pyquaternion
Requires-Dist: trollius
